bibli_ls/__init__.py
bibli_ls/bibli_config.py
bibli_ls/cli.py
bibli_ls/database.py
bibli_ls/server.py
bibli_ls/utils.py
bibli_ls/backends/backend.py
bibli_ls/backends/bibtex_backend.py
bibli_ls/backends/zotero_backend.py
bibli_ls-0.1.7.1.dist-info/LICENSE
bibli_ls-0.1.7.1.dist-info/METADATA
bibli_ls-0.1.7.1.dist-info/WHEEL
bibli_ls-0.1.7.1.dist-info/entry_points.txt
bibli_ls-0.1.7.1.dist-info/top_level.txt
bibli_ls-0.1.7.1.dist-info/RECORD
