Metadata-Version: 2.2
Name: bibli_ls
Version: 0.1.7.1
Summary: A simple LSP server for your bibliographies
Author-email: Kha Dinh <dalo2903@gmail.com>
Project-URL: Homepage, https://github.com/kha-dinh/bibli-ls
Project-URL: Issues, https://github.com/kha-dinh/bibli-ls/issues
Classifier: Programming Language :: Python :: 3
Classifier: License :: OSI Approved :: MIT License
Classifier: Operating System :: OS Independent
Requires-Python: >=3.12
License-File: LICENSE
Requires-Dist: bibtexparser==2.0.0b4
Requires-Dist: watchdog==6.0.0
Requires-Dist: pyzotero==1.5.25
Requires-Dist: py_markdown_table==1.2.0
Requires-Dist: pygls==2.0.0a2
Requires-Dist: tosholi==0.1.0
Requires-Dist: mdformat==0.7.19
Requires-Dist: ripgrepy==2.0.0
Requires-Dist: typing_extensions==4.12.2
Provides-Extra: doc
Requires-Dist: pydoc-markdown==4.8.2; extra == "doc"
